DQMaRC/Accuracy.py
DQMaRC/Completeness.py
DQMaRC/Consistency.py
DQMaRC/DataQuality.py
DQMaRC/Dimension.py
DQMaRC/Timeliness.py
DQMaRC/Uniqueness.py
DQMaRC/UtilitiesDQMaRC.py
DQMaRC/Validity.py
DQMaRC/__init__.py
DQMaRC/__version__.py
DQMaRC/app.py
DQMaRC/data/test_params_definitions.csv
DQMaRC/data/toy_df_DQ_results_full.csv
DQMaRC/data/toydf_subset.csv
DQMaRC/data/toydf_subset_test_params_24.05.16.csv
DQMaRC/data/lookups/LU_toydf_ICD10_v5.csv
DQMaRC/data/lookups/LU_toydf_M_stage.csv
DQMaRC/data/lookups/LU_toydf_gender.csv
DQMaRC/data/lookups/LU_toydf_tumour_stage.csv
docs/Makefile
docs/__init__.py
docs/docs_requirements.txt
docs/make.bat
DQMaRC-1.0.4.dist-info/LICENSE.md
DQMaRC-1.0.4.dist-info/LICENSE.txt
DQMaRC-1.0.4.dist-info/METADATA
DQMaRC-1.0.4.dist-info/WHEEL
DQMaRC-1.0.4.dist-info/entry_points.txt
DQMaRC-1.0.4.dist-info/top_level.txt
DQMaRC-1.0.4.dist-info/RECORD
