Metadata-Version: 2.1
Name: DQMaRC
Version: 1.0.4
Summary: A Python Tool for Structured Data Quality Profiling
Home-page: https://github.com/christie-nhs-data-science/DQMaRC
Author: Anthony Lighterness and Michael Adcock
Author-email: Anthony Lighterness <anthony.lighterness@nhs.net>, Michael Adcock <michael.adcock2@nhs.net>
Maintainer-email: Anthony Lighterness <tony.lighterness@gmail.com>, Michael Adcock <michael.adcock2@nhs.net>
License: Open Government License v3
Project-URL: Documentation, https://christie-nhs-data-science.github.io/DQMaRC/
Project-URL: Repository, https://github.com/christie-nhs-data-science/DQMaRC
Project-URL: Issues, https://github.com/christie-nhs-data-science/DQMaRC/issues
Keywords: data quality,data quality profiling
Classifier: Development Status :: 4 - Beta
Classifier: Intended Audience :: Developers
Classifier: Topic :: Software Development :: Build Tools
Classifier: License :: OSI Approved :: MIT License
Classifier: Programming Language :: Python :: 3.9
Classifier: Programming Language :: Python :: 3.10
Requires-Python: >=3.9
License-File: LICENSE.md
License-File: LICENSE.txt
Requires-Dist: pandas
Requires-Dist: numpy <2.0
Requires-Dist: ipywidgets
Requires-Dist: plotly
Requires-Dist: shiny
Requires-Dist: ipydatagrid
Requires-Dist: nbconvert
Requires-Dist: nbformat
Requires-Dist: jupyterlab
